cloudwatch_logging/CloudwatchLogging.py
cloudwatch_logging/ContextLogger.py
cloudwatch_logging/Filters.py
cloudwatch_logging/__init__.py
tests/__init__.py
tests/test_cloudwatch_logging.py
cloudwatch_logging-1.0.0.dist-info/LICENSE
cloudwatch_logging-1.0.0.dist-info/METADATA
cloudwatch_logging-1.0.0.dist-info/WHEEL
cloudwatch_logging-1.0.0.dist-info/top_level.txt
cloudwatch_logging-1.0.0.dist-info/RECORD
