Metadata-Version: 2.1
Name: cloudwatch-logging
Version: 1.0.0
Summary: A structured JSON logger that seamlessly interoperates with AWS Cloudwatch and other AWS services (e.g. Lambda)
Home-page: https://github.com/njedema/cloudwatch-logging/
Author: Nicolaas Jedema
Author-email: nj2681@gmail.com
License: UNKNOWN
Keywords: structured,logging,logger,json,cloudwatch,cloud,watch,AWS,aws,lambda
Platform: UNKNOWN
Classifier: Development Status :: 4 - Beta
Classifier: Programming Language :: Python :: 3
Classifier: License :: OSI Approved :: Apache Software License
Classifier: Intended Audience :: Developers
Classifier: Operating System :: OS Independent
Requires-Python: >=3.6
